MANIFEST.in
README.md
pyproject.toml
setup.cfg
setup.py
baseapp_cloudflare_stream_field/__init__.py
baseapp_cloudflare_stream_field/field.py
baseapp_cloudflare_stream_field/forms.py
baseapp_cloudflare_stream_field/rest_framework.py
baseapp_cloudflare_stream_field/stream.py
baseapp_cloudflare_stream_field/tasks.py
baseapp_cloudflare_stream_field/urls.py
baseapp_cloudflare_stream_field/views.py
baseapp_cloudflare_stream_field/widgets.py
baseapp_cloudflare_stream_field.egg-info/PKG-INFO
baseapp_cloudflare_stream_field.egg-info/SOURCES.txt
baseapp_cloudflare_stream_field.egg-info/dependency_links.txt
baseapp_cloudflare_stream_field.egg-info/requires.txt
baseapp_cloudflare_stream_field.egg-info/top_level.txt
baseapp_cloudflare_stream_field/static/baseapp_cloudflare_stream_field/js/baseapp_cloudflare_stream_field.js
baseapp_cloudflare_stream_field/static/baseapp_cloudflare_stream_field/js/tus.js
baseapp_cloudflare_stream_field/static/baseapp_cloudflare_stream_field/js/tus.js.map
baseapp_cloudflare_stream_field/static/baseapp_cloudflare_stream_field/js/tus.min.js
baseapp_cloudflare_stream_field/static/baseapp_cloudflare_stream_field/js/tus.min.js.map
baseapp_cloudflare_stream_field/templates/baseapp_cloudflare_stream_field/admin_async_file_input.html
baseapp_cloudflare_stream_field/tests/__init__.py
baseapp_cloudflare_stream_field/tests/conftest.py
baseapp_cloudflare_stream_field/tests/settings.py
baseapp_cloudflare_stream_field/tests/test_migration_health_check.py
testproject/__init__.py
testproject/settings.py